<?xml version="1.0" ?>
<Root_Node UI_File_Name="SpellOverview.xml" Texture_Path="" Screen_X="1024" Screen_Y="768">
    <Style Style="65536" />
    <BaseWndProperty WindowID="1" WindowText="" WindowLeft="0" WindowTop="0" WindowHeight="477" WindowWidth="405" Visible="1" FixSize="0" Drag="0" Drop="0">
        <BackGroundMap BGmap="Slot32.dds">
            <NorUV NorUVLeft="0" NorUVTop="0" NorUVWidth="0" NorUVHeight="0" />
        </BackGroundMap>
        <Container_Node Child_Cnt="63">
            <Style ParentNode="1" CtrlType="268435456" />
            <BaseWndProperty WindowID="10000" WindowText="" WindowLeft="0" WindowTop="0" WindowHeight="477" WindowWidth="405" Visible="1" FixSize="0" Drag="0" Drop="0">
                <BackGroundMap BGmap="uiobj12.dds">
                    <NorUV NorUVLeft="1017" NorUVTop="4" NorUVWidth="477" NorUVHeight="405" />
                </BackGroundMap>
                <BaseCtrlProperty Tips="" FontFace="細明體" FontSize="10" FontColor="0" FontStyle="0" />
                <PictureNode TextureClampMode="0">
                    <ForegroundUV ForegroundUVLeft="0" ForegroundUVTop="0" ForegroundUVWidth="10" ForegroundUVHeight="10" />
                </PictureNode>
            </BaseWndProperty>
            <Style ParentNode="10000" CtrlType="268435456" />
            <BaseWndProperty WindowID="11000" WindowText="" WindowLeft="21" WindowTop="65" WindowHeight="95" WindowWidth="185" Visible="1" FixSize="0" Drag="0" Drop="0">
                <BackGroundMap BGmap="Slot32.dds">
                    <NorUV NorUVLeft="0" NorUVTop="0" NorUVWidth="10" NorUVHeight="10" />
                </BackGroundMap>
                <BaseCtrlProperty Tips="" FontFace="細明體" FontSize="10" FontColor="0" FontStyle="0" />
                <PictureNode TextureClampMode="0">
                    <ForegroundUV ForegroundUVLeft="0" ForegroundUVTop="0" ForegroundUVWidth="10" ForegroundUVHeight="10" />
                </PictureNode>
            </BaseWndProperty>
            <Style ParentNode="10000" CtrlType="268435456" />
            <BaseWndProperty WindowID="11001" WindowText="" WindowLeft="22" WindowTop="65" WindowHeight="93" WindowWidth="16" Visible="1" FixSize="0" Drag="0" Drop="0">
                <BackGroundMap BGmap="uiobj01.dds">
                    <NorUV NorUVLeft="255" NorUVTop="985" NorUVWidth="100" NorUVHeight="16" />
                </BackGroundMap>
                <BaseCtrlProperty Tips="" FontFace="細明體" FontSize="10" FontColor="0" FontStyle="0" />
                <PictureNode TextureClampMode="0">
                    <ForegroundUV ForegroundUVLeft="0" ForegroundUVTop="0" ForegroundUVWidth="10" ForegroundUVHeight="10" />
                </PictureNode>
            </BaseWndProperty>
            <Style ParentNode="10000" CtrlType="268435456" />
            <BaseWndProperty WindowID="11002" WindowText="" WindowLeft="21" WindowTop="65" WindowHeight="95" WindowWidth="290" Visible="1" FixSize="0" Drag="0" Drop="0">
                <BackGroundMap BGmap="Slot32.dds">
                    <NorUV NorUVLeft="0" NorUVTop="0" NorUVWidth="10" NorUVHeight="10" />
                </BackGroundMap>
                <BaseCtrlProperty Tips="" FontFace="細明體" FontSize="10" FontColor="0" FontStyle="0" />
                <PictureNode TextureClampMode="0">
                    <ForegroundUV ForegroundUVLeft="0" ForegroundUVTop="0" ForegroundUVWidth="10" ForegroundUVHeight="10" />
                </PictureNode>
            </BaseWndProperty>
            <Style ParentNode="10000" CtrlType="268435456" />
            <BaseWndProperty WindowID="11003" WindowText="" WindowLeft="236" WindowTop="30" WindowHeight="65" WindowWidth="19" Visible="1" FixSize="0" Drag="0" Drop="0">
                <BackGroundMap BGmap="uiobj12.dds">
                    <NorUV NorUVLeft="1198" NorUVTop="34" NorUVWidth="65" NorUVHeight="19" />
                </BackGroundMap>
                <BaseCtrlProperty Tips="" FontFace="細明體" FontSize="10" FontColor="0" FontStyle="0" />
                <PictureNode TextureClampMode="0">
                    <ForegroundUV ForegroundUVLeft="0" ForegroundUVTop="0" ForegroundUVWidth="10" ForegroundUVHeight="10" />
                </PictureNode>
            </BaseWndProperty>
            <Style ParentNode="10000" CtrlType="268435456" />
            <BaseWndProperty WindowID="11004" WindowText="" WindowLeft="290" WindowTop="30" WindowHeight="65" WindowWidth="19" Visible="1" FixSize="0" Drag="0" Drop="0">
                <BackGroundMap BGmap="uiobj12.dds">
                    <NorUV NorUVLeft="1198" NorUVTop="34" NorUVWidth="66" NorUVHeight="19" />
                </BackGroundMap>
                <BaseCtrlProperty Tips="" FontFace="細明體" FontSize="10" FontColor="0" FontStyle="0" />
                <PictureNode TextureClampMode="0">
                    <ForegroundUV ForegroundUVLeft="0" ForegroundUVTop="0" ForegroundUVWidth="10" ForegroundUVHeight="10" />
                </PictureNode>
            </BaseWndProperty>
            <Style ParentNode="10000" CtrlType="33554432" />
            <BaseWndProperty WindowID="20000" WindowText="技能總覽" WindowLeft="17" WindowTop="4" WindowHeight="200" WindowWidth="16" Visible="1" FixSize="0" Drag="0" Drop="0">
                <BackGroundMap BGmap="Slot32.dds">
                    <NorUV NorUVLeft="0" NorUVTop="0" NorUVWidth="0" NorUVHeight="0" />
                </BackGroundMap>
                <BaseCtrlProperty Tips="" FontFace="細明體" FontSize="10" FontColor="65535" FontStyle="1" />
                <TextNode TextAlign="0" MultiLine="0" />
            </BaseWndProperty>
            <Style ParentNode="10000" CtrlType="16777216" />
            <BaseWndProperty WindowID="25000" WindowText="" WindowLeft="128" WindowTop="61" WindowHeight="313" WindowWidth="36" Visible="1" FixSize="0" Drag="0" Drop="0">
                <BackGroundMap BGmap="Slot32.dds">
                    <NorUV NorUVLeft="0" NorUVTop="0" NorUVWidth="0" NorUVHeight="0" />
                </BackGroundMap>
                <BaseCtrlProperty Tips="" FontFace="細明體" FontSize="10" FontColor="16777215" FontStyle="0" />
                <EditNode ReadOnly="1" />
                <MultiEditNode />
            </BaseWndProperty>
            <Style ParentNode="10000" CtrlType="262144" />
            <BaseWndProperty WindowID="30000" WindowText="" WindowLeft="443" WindowTop="59" WindowHeight="13" WindowWidth="9" Visible="1" FixSize="0" Drag="0" Drop="0">
                <BackGroundMap BGmap="main.dds">
                    <NorUV NorUVLeft="933" NorUVTop="312" NorUVWidth="13" NorUVHeight="9" />
                </BackGroundMap>
                <BaseCtrlProperty Tips="" FontFace="細明體" FontSize="10" FontColor="16777215" FontStyle="0" />
                <ButtonNode BtnState="0">
                    <FocusUV FocusUVLeft="950" FocusUVTop="312" FocusUVWidth="13" FocusUVHeight="9" />
                    <DownUV DownUVLeft="967" DownUVTop="312" DownUVWidth="13" DownUVHeight="9" />
                    <DisableUV DisableUVLeft="933" DisableUVTop="312" DisableUVWidth="13" DisableUVHeight="9" />
                </ButtonNode>
            </BaseWndProperty>
            <Style ParentNode="10000" CtrlType="262144" />
            <BaseWndProperty WindowID="30001" WindowText="" WindowLeft="443" WindowTop="87" WindowHeight="13" WindowWidth="9" Visible="1" FixSize="0" Drag="0" Drop="0">
                <BackGroundMap BGmap="main.dds">
                    <NorUV NorUVLeft="933" NorUVTop="323" NorUVWidth="13" NorUVHeight="9" />
                </BackGroundMap>
                <BaseCtrlProperty Tips="" FontFace="細明體" FontSize="10" FontColor="16777215" FontStyle="0" />
                <ButtonNode BtnState="0">
                    <FocusUV FocusUVLeft="950" FocusUVTop="323" FocusUVWidth="13" FocusUVHeight="9" />
                    <DownUV DownUVLeft="967" DownUVTop="323" DownUVWidth="13" DownUVHeight="9" />
                    <DisableUV DisableUVLeft="933" DisableUVTop="323" DisableUVWidth="13" DisableUVHeight="9" />
                </ButtonNode>
            </BaseWndProperty>
            <Style ParentNode="10000" CtrlType="2097152" />
            <BaseWndProperty WindowID="35000" WindowText="" WindowLeft="444" WindowTop="69" WindowHeight="11" WindowWidth="16" Visible="1" FixSize="0" Drag="0" Drop="0">
                <BackGroundMap BGmap="main.dds">
                    <NorUV NorUVLeft="0" NorUVTop="0" NorUVWidth="0" NorUVHeight="0" />
                </BackGroundMap>
                <BaseCtrlProperty Tips="" FontFace="細明體" FontSize="10" FontColor="0" FontStyle="0" />
                <TrackNode Max="2" Min="0" cur="0" Page="2">
                    <ThumbUV ThumbUVLeft="986" ThumbUVTop="300" ThumbUVWidth="11" ThumbUVHeight="51" />
                </TrackNode>
            </BaseWndProperty>
            <Style ParentNode="10000" CtrlType="262144" />
            <BaseWndProperty WindowID="31000" WindowText="" WindowLeft="445" WindowTop="4" WindowHeight="16" WindowWidth="15" Visible="1" FixSize="0" Drag="0" Drop="0">
                <BackGroundMap BGmap="main.dds">
                    <NorUV NorUVLeft="931" NorUVTop="337" NorUVWidth="16" NorUVHeight="15" />
                </BackGroundMap>
                <BaseCtrlProperty Tips="" FontFace="細明體" FontSize="10" FontColor="16777215" FontStyle="0" />
                <ButtonNode BtnState="0">
                    <FocusUV FocusUVLeft="949" FocusUVTop="337" FocusUVWidth="16" FocusUVHeight="15" />
                    <DownUV DownUVLeft="967" DownUVTop="337" DownUVWidth="16" DownUVHeight="15" />
                    <DisableUV DisableUVLeft="0" DisableUVTop="0" DisableUVWidth="10" DisableUVHeight="10" />
                </ButtonNode>
            </BaseWndProperty>
            <Style ParentNode="10000" CtrlType="262144" />
            <BaseWndProperty WindowID="31001" WindowText="" WindowLeft="397" WindowTop="368" WindowHeight="64" WindowWidth="18" Visible="1" FixSize="0" Drag="0" Drop="0">
                <BackGroundMap BGmap="main.dds">
                    <NorUV NorUVLeft="734" NorUVTop="204" NorUVWidth="64" NorUVHeight="18" />
                </BackGroundMap>
                <BaseCtrlProperty Tips="" FontFace="細明體" FontSize="10" FontColor="16777215" FontStyle="1" />
                <ButtonNode BtnState="0">
                    <FocusUV FocusUVLeft="734" FocusUVTop="226" FocusUVWidth="64" FocusUVHeight="18" />
                    <DownUV DownUVLeft="734" DownUVTop="248" DownUVWidth="64" DownUVHeight="18" />
                    <DisableUV DisableUVLeft="734" DisableUVTop="270" DisableUVWidth="64" DisableUVHeight="18" />
                </ButtonNode>
            </BaseWndProperty>
            <Style ParentNode="10000" CtrlType="262144" />
            <BaseWndProperty WindowID="31002" WindowText="" WindowLeft="441" WindowTop="29" WindowHeight="16" WindowWidth="16" Visible="1" FixSize="0" Drag="0" Drop="0">
                <BackGroundMap BGmap="main.dds">
                    <NorUV NorUVLeft="999" NorUVTop="190" NorUVWidth="16" NorUVHeight="16" />
                </BackGroundMap>
                <BaseCtrlProperty Tips="" FontFace="細明體" FontSize="10" FontColor="16777215" FontStyle="0" />
                <ButtonNode BtnState="0">
                    <FocusUV FocusUVLeft="999" FocusUVTop="207" FocusUVWidth="16" FocusUVHeight="16" />
                    <DownUV DownUVLeft="999" DownUVTop="224" DownUVWidth="16" DownUVHeight="16" />
                    <DisableUV DisableUVLeft="999" DisableUVTop="241" DisableUVWidth="16" DisableUVHeight="16" />
                </ButtonNode>
            </BaseWndProperty>
            <Style ParentNode="10000" CtrlType="131072" />
            <BaseWndProperty WindowID="32000" WindowText="2206" WindowLeft="13" WindowTop="31" WindowHeight="64" WindowWidth="18" Visible="1" FixSize="0" Drag="0" Drop="0">
                <BackGroundMap BGmap="main.dds">
                    <NorUV NorUVLeft="880" NorUVTop="196" NorUVWidth="64" NorUVHeight="18" />
                </BackGroundMap>
                <BaseCtrlProperty Tips="" FontFace="細明體" FontSize="10" FontColor="0" FontStyle="0" />
                <ButtonNode BtnState="0">
                    <FocusUV FocusUVLeft="880" FocusUVTop="244" FocusUVWidth="64" FocusUVHeight="18" />
                    <DownUV DownUVLeft="880" DownUVTop="196" DownUVWidth="64" DownUVHeight="18" />
                    <DisableUV DisableUVLeft="880" DisableUVTop="196" DisableUVWidth="64" DisableUVHeight="18" />
                </ButtonNode>
            </BaseWndProperty>
            <Style ParentNode="10000" CtrlType="131072" />
            <BaseWndProperty WindowID="32001" WindowText="2001" WindowLeft="68" WindowTop="31" WindowHeight="64" WindowWidth="18" Visible="1" FixSize="0" Drag="0" Drop="0">
                <BackGroundMap BGmap="main.dds">
                    <NorUV NorUVLeft="880" NorUVTop="196" NorUVWidth="64" NorUVHeight="18" />
                </BackGroundMap>
                <BaseCtrlProperty Tips="" FontFace="細明體" FontSize="10" FontColor="0" FontStyle="0" />
                <ButtonNode BtnState="0">
                    <FocusUV FocusUVLeft="880" FocusUVTop="244" FocusUVWidth="64" FocusUVHeight="18" />
                    <DownUV DownUVLeft="880" DownUVTop="196" DownUVWidth="64" DownUVHeight="18" />
                    <DisableUV DisableUVLeft="880" DisableUVTop="196" DisableUVWidth="64" DisableUVHeight="18" />
                </ButtonNode>
            </BaseWndProperty>
            <Style ParentNode="10000" CtrlType="131072" />
            <BaseWndProperty WindowID="32002" WindowText="2002" WindowLeft="123" WindowTop="31" WindowHeight="64" WindowWidth="18" Visible="1" FixSize="0" Drag="0" Drop="0">
                <BackGroundMap BGmap="main.dds">
                    <NorUV NorUVLeft="880" NorUVTop="196" NorUVWidth="64" NorUVHeight="18" />
                </BackGroundMap>
                <BaseCtrlProperty Tips="" FontFace="細明體" FontSize="9" FontColor="0" FontStyle="0" />
                <ButtonNode BtnState="0">
                    <FocusUV FocusUVLeft="0" FocusUVTop="0" FocusUVWidth="10" FocusUVHeight="10" />
                    <DownUV DownUVLeft="880" DownUVTop="196" DownUVWidth="64" DownUVHeight="18" />
                    <DisableUV DisableUVLeft="880" DisableUVTop="196" DisableUVWidth="64" DisableUVHeight="18" />
                </ButtonNode>
            </BaseWndProperty>
            <Style ParentNode="10000" CtrlType="131072" />
            <BaseWndProperty WindowID="32003" WindowText="2003" WindowLeft="178" WindowTop="31" WindowHeight="64" WindowWidth="18" Visible="1" FixSize="0" Drag="0" Drop="0">
                <BackGroundMap BGmap="main.dds">
                    <NorUV NorUVLeft="880" NorUVTop="196" NorUVWidth="64" NorUVHeight="18" />
                </BackGroundMap>
                <BaseCtrlProperty Tips="" FontFace="細明體" FontSize="10" FontColor="0" FontStyle="0" />
                <ButtonNode BtnState="0">
                    <FocusUV FocusUVLeft="880" FocusUVTop="244" FocusUVWidth="64" FocusUVHeight="18" />
                    <DownUV DownUVLeft="880" DownUVTop="196" DownUVWidth="64" DownUVHeight="18" />
                    <DisableUV DisableUVLeft="880" DisableUVTop="196" DisableUVWidth="64" DisableUVHeight="18" />
                </ButtonNode>
            </BaseWndProperty>
            <Style ParentNode="10000" CtrlType="131072" />
            <BaseWndProperty WindowID="32004" WindowText="2003" WindowLeft="233" WindowTop="31" WindowHeight="64" WindowWidth="18" Visible="1" FixSize="0" Drag="0" Drop="0">
                <BackGroundMap BGmap="main.dds">
                    <NorUV NorUVLeft="880" NorUVTop="196" NorUVWidth="64" NorUVHeight="18" />
                </BackGroundMap>
                <BaseCtrlProperty Tips="" FontFace="細明體" FontSize="10" FontColor="0" FontStyle="0" />
                <ButtonNode BtnState="0">
                    <FocusUV FocusUVLeft="880" FocusUVTop="244" FocusUVWidth="64" FocusUVHeight="18" />
                    <DownUV DownUVLeft="880" DownUVTop="196" DownUVWidth="64" DownUVHeight="18" />
                    <DisableUV DisableUVLeft="880" DisableUVTop="196" DisableUVWidth="64" DisableUVHeight="18" />
                </ButtonNode>
            </BaseWndProperty>
            <Style ParentNode="10000" CtrlType="131072" />
            <BaseWndProperty WindowID="32005" WindowText="2003" WindowLeft="287" WindowTop="31" WindowHeight="64" WindowWidth="18" Visible="1" FixSize="0" Drag="0" Drop="0">
                <BackGroundMap BGmap="main.dds">
                    <NorUV NorUVLeft="880" NorUVTop="196" NorUVWidth="64" NorUVHeight="18" />
                </BackGroundMap>
                <BaseCtrlProperty Tips="" FontFace="細明體" FontSize="10" FontColor="0" FontStyle="0" />
                <ButtonNode BtnState="0">
                    <FocusUV FocusUVLeft="880" FocusUVTop="244" FocusUVWidth="64" FocusUVHeight="18" />
                    <DownUV DownUVLeft="880" DownUVTop="196" DownUVWidth="64" DownUVHeight="18" />
                    <DisableUV DisableUVLeft="880" DisableUVTop="196" DisableUVWidth="64" DisableUVHeight="18" />
                </ButtonNode>
            </BaseWndProperty>
            <Style ParentNode="10000" CtrlType="268435456" />
            <BaseWndProperty WindowID="40003" WindowText="" WindowLeft="130" WindowTop="105" WindowHeight="159" WindowWidth="41" Visible="1" FixSize="0" Drag="0" Drop="0">
                <BackGroundMap BGmap="uiobj12.dds">
                    <NorUV NorUVLeft="1147" NorUVTop="109" NorUVWidth="159" NorUVHeight="41" />
                </BackGroundMap>
                <BaseCtrlProperty Tips="" FontFace="細明體" FontSize="10" FontColor="0" FontStyle="0" />
                <PictureNode TextureClampMode="0">
                    <ForegroundUV ForegroundUVLeft="0" ForegroundUVTop="0" ForegroundUVWidth="10" ForegroundUVHeight="10" />
                </PictureNode>
            </BaseWndProperty>
            <Style ParentNode="40003" CtrlType="536870912" />
            <BaseWndProperty WindowID="40000" WindowText="" WindowLeft="136" WindowTop="110" WindowHeight="32" WindowWidth="32" Visible="1" FixSize="0" Drag="0" Drop="0">
                <BackGroundMap BGmap="Slot32.dds">
                    <NorUV NorUVLeft="0" NorUVTop="0" NorUVWidth="32" NorUVHeight="32" />
                </BackGroundMap>
                <BaseCtrlProperty Tips="" FontFace="細明體" FontSize="10" FontColor="0" FontStyle="0" />
                <SlotNode />
            </BaseWndProperty>
            <Style ParentNode="40003" CtrlType="33554432" />
            <BaseWndProperty WindowID="40001" WindowText="" WindowLeft="172" WindowTop="110" WindowHeight="110" WindowWidth="16" Visible="1" FixSize="0" Drag="0" Drop="0">
                <BackGroundMap BGmap="Slot32.dds">
                    <NorUV NorUVLeft="0" NorUVTop="0" NorUVWidth="0" NorUVHeight="0" />
                </BackGroundMap>
                <BaseCtrlProperty Tips="" FontFace="細明體" FontSize="10" FontColor="16777215" FontStyle="1" />
                <TextNode TextAlign="0" MultiLine="0" />
            </BaseWndProperty>
            <Style ParentNode="40003" CtrlType="33554432" />
            <BaseWndProperty WindowID="40002" WindowText="" WindowLeft="172" WindowTop="125" WindowHeight="110" WindowWidth="16" Visible="1" FixSize="0" Drag="0" Drop="0">
                <BackGroundMap BGmap="Slot32.dds">
                    <NorUV NorUVLeft="0" NorUVTop="0" NorUVWidth="0" NorUVHeight="0" />
                </BackGroundMap>
                <BaseCtrlProperty Tips="" FontFace="細明體" FontSize="10" FontColor="16777215" FontStyle="1" />
                <TextNode TextAlign="0" MultiLine="0" />
            </BaseWndProperty>
            <Style ParentNode="10000" CtrlType="268435456" />
            <BaseWndProperty WindowID="40008" WindowText="" WindowLeft="293" WindowTop="105" WindowHeight="159" WindowWidth="41" Visible="1" FixSize="0" Drag="0" Drop="0">
                <BackGroundMap BGmap="uiobj12.dds">
                    <NorUV NorUVLeft="1147" NorUVTop="109" NorUVWidth="159" NorUVHeight="41" />
                </BackGroundMap>
                <BaseCtrlProperty Tips="" FontFace="細明體" FontSize="10" FontColor="0" FontStyle="0" />
                <PictureNode TextureClampMode="0">
                    <ForegroundUV ForegroundUVLeft="0" ForegroundUVTop="0" ForegroundUVWidth="10" ForegroundUVHeight="10" />
                </PictureNode>
            </BaseWndProperty>
            <Style ParentNode="40008" CtrlType="536870912" />
            <BaseWndProperty WindowID="40005" WindowText="" WindowLeft="299" WindowTop="110" WindowHeight="32" WindowWidth="32" Visible="1" FixSize="0" Drag="0" Drop="0">
                <BackGroundMap BGmap="Slot32.dds">
                    <NorUV NorUVLeft="0" NorUVTop="0" NorUVWidth="32" NorUVHeight="32" />
                </BackGroundMap>
                <BaseCtrlProperty Tips="" FontFace="細明體" FontSize="10" FontColor="0" FontStyle="0" />
                <SlotNode />
            </BaseWndProperty>
            <Style ParentNode="40008" CtrlType="33554432" />
            <BaseWndProperty WindowID="40006" WindowText="" WindowLeft="335" WindowTop="110" WindowHeight="110" WindowWidth="16" Visible="1" FixSize="0" Drag="0" Drop="0">
                <BackGroundMap BGmap="Slot32.dds">
                    <NorUV NorUVLeft="0" NorUVTop="0" NorUVWidth="0" NorUVHeight="0" />
                </BackGroundMap>
                <BaseCtrlProperty Tips="" FontFace="細明體" FontSize="10" FontColor="16777215" FontStyle="1" />
                <TextNode TextAlign="0" MultiLine="0" />
            </BaseWndProperty>
            <Style ParentNode="40008" CtrlType="33554432" />
            <BaseWndProperty WindowID="40007" WindowText="" WindowLeft="335" WindowTop="125" WindowHeight="110" WindowWidth="16" Visible="1" FixSize="0" Drag="0" Drop="0">
                <BackGroundMap BGmap="Slot32.dds">
                    <NorUV NorUVLeft="0" NorUVTop="0" NorUVWidth="0" NorUVHeight="0" />
                </BackGroundMap>
                <BaseCtrlProperty Tips="" FontFace="細明體" FontSize="10" FontColor="16777215" FontStyle="1" />
                <TextNode TextAlign="0" MultiLine="0" />
            </BaseWndProperty>
            <Style ParentNode="10000" CtrlType="268435456" />
            <BaseWndProperty WindowID="40013" WindowText="" WindowLeft="130" WindowTop="150" WindowHeight="159" WindowWidth="41" Visible="1" FixSize="0" Drag="0" Drop="0">
                <BackGroundMap BGmap="uiobj12.dds">
                    <NorUV NorUVLeft="1147" NorUVTop="109" NorUVWidth="159" NorUVHeight="41" />
                </BackGroundMap>
                <BaseCtrlProperty Tips="" FontFace="細明體" FontSize="10" FontColor="0" FontStyle="0" />
                <PictureNode TextureClampMode="0">
                    <ForegroundUV ForegroundUVLeft="0" ForegroundUVTop="0" ForegroundUVWidth="10" ForegroundUVHeight="10" />
                </PictureNode>
            </BaseWndProperty>
            <Style ParentNode="40013" CtrlType="536870912" />
            <BaseWndProperty WindowID="40010" WindowText="" WindowLeft="136" WindowTop="156" WindowHeight="32" WindowWidth="32" Visible="1" FixSize="0" Drag="0" Drop="0">
                <BackGroundMap BGmap="Slot32.dds">
                    <NorUV NorUVLeft="0" NorUVTop="0" NorUVWidth="32" NorUVHeight="32" />
                </BackGroundMap>
                <BaseCtrlProperty Tips="" FontFace="細明體" FontSize="10" FontColor="0" FontStyle="0" />
                <SlotNode />
            </BaseWndProperty>
            <Style ParentNode="40013" CtrlType="33554432" />
            <BaseWndProperty WindowID="40011" WindowText="" WindowLeft="172" WindowTop="155" WindowHeight="110" WindowWidth="16" Visible="1" FixSize="0" Drag="0" Drop="0">
                <BackGroundMap BGmap="Slot32.dds">
                    <NorUV NorUVLeft="0" NorUVTop="0" NorUVWidth="0" NorUVHeight="0" />
                </BackGroundMap>
                <BaseCtrlProperty Tips="" FontFace="細明體" FontSize="10" FontColor="16777215" FontStyle="1" />
                <TextNode TextAlign="0" MultiLine="0" />
            </BaseWndProperty>
            <Style ParentNode="40013" CtrlType="33554432" />
            <BaseWndProperty WindowID="40012" WindowText="" WindowLeft="172" WindowTop="170" WindowHeight="110" WindowWidth="16" Visible="1" FixSize="0" Drag="0" Drop="0">
                <BackGroundMap BGmap="Slot32.dds">
                    <NorUV NorUVLeft="0" NorUVTop="0" NorUVWidth="0" NorUVHeight="0" />
                </BackGroundMap>
                <BaseCtrlProperty Tips="" FontFace="細明體" FontSize="10" FontColor="16777215" FontStyle="1" />
                <TextNode TextAlign="0" MultiLine="0" />
            </BaseWndProperty>
            <Style ParentNode="10000" CtrlType="268435456" />
            <BaseWndProperty WindowID="40018" WindowText="" WindowLeft="293" WindowTop="150" WindowHeight="159" WindowWidth="41" Visible="1" FixSize="0" Drag="0" Drop="0">
                <BackGroundMap BGmap="uiobj12.dds">
                    <NorUV NorUVLeft="1147" NorUVTop="109" NorUVWidth="159" NorUVHeight="41" />
                </BackGroundMap>
                <BaseCtrlProperty Tips="" FontFace="細明體" FontSize="10" FontColor="0" FontStyle="0" />
                <PictureNode TextureClampMode="0">
                    <ForegroundUV ForegroundUVLeft="0" ForegroundUVTop="0" ForegroundUVWidth="10" ForegroundUVHeight="10" />
                </PictureNode>
            </BaseWndProperty>
            <Style ParentNode="40018" CtrlType="536870912" />
            <BaseWndProperty WindowID="40015" WindowText="" WindowLeft="299" WindowTop="156" WindowHeight="32" WindowWidth="32" Visible="1" FixSize="0" Drag="0" Drop="0">
                <BackGroundMap BGmap="Slot32.dds">
                    <NorUV NorUVLeft="0" NorUVTop="0" NorUVWidth="32" NorUVHeight="32" />
                </BackGroundMap>
                <BaseCtrlProperty Tips="" FontFace="細明體" FontSize="10" FontColor="0" FontStyle="0" />
                <SlotNode />
            </BaseWndProperty>
            <Style ParentNode="40018" CtrlType="33554432" />
            <BaseWndProperty WindowID="40016" WindowText="" WindowLeft="335" WindowTop="155" WindowHeight="110" WindowWidth="16" Visible="1" FixSize="0" Drag="0" Drop="0">
                <BackGroundMap BGmap="Slot32.dds">
                    <NorUV NorUVLeft="0" NorUVTop="0" NorUVWidth="0" NorUVHeight="0" />
                </BackGroundMap>
                <BaseCtrlProperty Tips="" FontFace="細明體" FontSize="10" FontColor="16777215" FontStyle="1" />
                <TextNode TextAlign="0" MultiLine="0" />
            </BaseWndProperty>
            <Style ParentNode="40018" CtrlType="33554432" />
            <BaseWndProperty WindowID="40017" WindowText="" WindowLeft="335" WindowTop="170" WindowHeight="110" WindowWidth="16" Visible="1" FixSize="0" Drag="0" Drop="0">
                <BackGroundMap BGmap="Slot32.dds">
                    <NorUV NorUVLeft="0" NorUVTop="0" NorUVWidth="0" NorUVHeight="0" />
                </BackGroundMap>
                <BaseCtrlProperty Tips="" FontFace="細明體" FontSize="10" FontColor="16777215" FontStyle="1" />
                <TextNode TextAlign="0" MultiLine="0" />
            </BaseWndProperty>
            <Style ParentNode="10000" CtrlType="268435456" />
            <BaseWndProperty WindowID="40023" WindowText="" WindowLeft="130" WindowTop="195" WindowHeight="159" WindowWidth="41" Visible="1" FixSize="0" Drag="0" Drop="0">
                <BackGroundMap BGmap="uiobj12.dds">
                    <NorUV NorUVLeft="1147" NorUVTop="109" NorUVWidth="159" NorUVHeight="41" />
                </BackGroundMap>
                <BaseCtrlProperty Tips="" FontFace="細明體" FontSize="10" FontColor="0" FontStyle="0" />
                <PictureNode TextureClampMode="0">
                    <ForegroundUV ForegroundUVLeft="0" ForegroundUVTop="0" ForegroundUVWidth="10" ForegroundUVHeight="10" />
                </PictureNode>
            </BaseWndProperty>
            <Style ParentNode="40023" CtrlType="536870912" />
            <BaseWndProperty WindowID="40020" WindowText="" WindowLeft="136" WindowTop="199" WindowHeight="32" WindowWidth="32" Visible="1" FixSize="0" Drag="0" Drop="0">
                <BackGroundMap BGmap="Slot32.dds">
                    <NorUV NorUVLeft="0" NorUVTop="0" NorUVWidth="32" NorUVHeight="32" />
                </BackGroundMap>
                <BaseCtrlProperty Tips="" FontFace="細明體" FontSize="10" FontColor="0" FontStyle="0" />
                <SlotNode />
            </BaseWndProperty>
            <Style ParentNode="40023" CtrlType="33554432" />
            <BaseWndProperty WindowID="40021" WindowText="" WindowLeft="172" WindowTop="200" WindowHeight="110" WindowWidth="16" Visible="1" FixSize="0" Drag="0" Drop="0">
                <BackGroundMap BGmap="Slot32.dds">
                    <NorUV NorUVLeft="0" NorUVTop="0" NorUVWidth="0" NorUVHeight="0" />
                </BackGroundMap>
                <BaseCtrlProperty Tips="" FontFace="細明體" FontSize="10" FontColor="16777215" FontStyle="1" />
                <TextNode TextAlign="0" MultiLine="0" />
            </BaseWndProperty>
            <Style ParentNode="40023" CtrlType="33554432" />
            <BaseWndProperty WindowID="40022" WindowText="" WindowLeft="172" WindowTop="215" WindowHeight="110" WindowWidth="16" Visible="1" FixSize="0" Drag="0" Drop="0">
                <BackGroundMap BGmap="Slot32.dds">
                    <NorUV NorUVLeft="0" NorUVTop="0" NorUVWidth="0" NorUVHeight="0" />
                </BackGroundMap>
                <BaseCtrlProperty Tips="" FontFace="細明體" FontSize="10" FontColor="16777215" FontStyle="1" />
                <TextNode TextAlign="0" MultiLine="0" />
            </BaseWndProperty>
            <Style ParentNode="10000" CtrlType="268435456" />
            <BaseWndProperty WindowID="40028" WindowText="" WindowLeft="293" WindowTop="195" WindowHeight="159" WindowWidth="41" Visible="1" FixSize="0" Drag="0" Drop="0">
                <BackGroundMap BGmap="uiobj12.dds">
                    <NorUV NorUVLeft="1147" NorUVTop="109" NorUVWidth="159" NorUVHeight="41" />
                </BackGroundMap>
                <BaseCtrlProperty Tips="" FontFace="細明體" FontSize="10" FontColor="0" FontStyle="0" />
                <PictureNode TextureClampMode="0">
                    <ForegroundUV ForegroundUVLeft="0" ForegroundUVTop="0" ForegroundUVWidth="10" ForegroundUVHeight="10" />
                </PictureNode>
            </BaseWndProperty>
            <Style ParentNode="40028" CtrlType="536870912" />
            <BaseWndProperty WindowID="40025" WindowText="" WindowLeft="299" WindowTop="199" WindowHeight="32" WindowWidth="32" Visible="1" FixSize="0" Drag="0" Drop="0">
                <BackGroundMap BGmap="Slot32.dds">
                    <NorUV NorUVLeft="0" NorUVTop="0" NorUVWidth="32" NorUVHeight="32" />
                </BackGroundMap>
                <BaseCtrlProperty Tips="" FontFace="細明體" FontSize="10" FontColor="0" FontStyle="0" />
                <SlotNode />
            </BaseWndProperty>
            <Style ParentNode="40028" CtrlType="33554432" />
            <BaseWndProperty WindowID="40026" WindowText="" WindowLeft="335" WindowTop="200" WindowHeight="110" WindowWidth="16" Visible="1" FixSize="0" Drag="0" Drop="0">
                <BackGroundMap BGmap="Slot32.dds">
                    <NorUV NorUVLeft="0" NorUVTop="0" NorUVWidth="0" NorUVHeight="0" />
                </BackGroundMap>
                <BaseCtrlProperty Tips="" FontFace="細明體" FontSize="10" FontColor="16777215" FontStyle="1" />
                <TextNode TextAlign="0" MultiLine="0" />
            </BaseWndProperty>
            <Style ParentNode="40028" CtrlType="33554432" />
            <BaseWndProperty WindowID="40027" WindowText="" WindowLeft="335" WindowTop="215" WindowHeight="110" WindowWidth="16" Visible="1" FixSize="0" Drag="0" Drop="0">
                <BackGroundMap BGmap="Slot32.dds">
                    <NorUV NorUVLeft="0" NorUVTop="0" NorUVWidth="0" NorUVHeight="0" />
                </BackGroundMap>
                <BaseCtrlProperty Tips="" FontFace="細明體" FontSize="10" FontColor="16777215" FontStyle="1" />
                <TextNode TextAlign="0" MultiLine="0" />
            </BaseWndProperty>
            <Style ParentNode="10000" CtrlType="268435456" />
            <BaseWndProperty WindowID="40033" WindowText="" WindowLeft="130" WindowTop="240" WindowHeight="159" WindowWidth="41" Visible="1" FixSize="0" Drag="0" Drop="0">
                <BackGroundMap BGmap="uiobj12.dds">
                    <NorUV NorUVLeft="1147" NorUVTop="109" NorUVWidth="159" NorUVHeight="41" />
                </BackGroundMap>
                <BaseCtrlProperty Tips="" FontFace="細明體" FontSize="10" FontColor="0" FontStyle="0" />
                <PictureNode TextureClampMode="0">
                    <ForegroundUV ForegroundUVLeft="0" ForegroundUVTop="0" ForegroundUVWidth="10" ForegroundUVHeight="10" />
                </PictureNode>
            </BaseWndProperty>
            <Style ParentNode="40033" CtrlType="536870912" />
            <BaseWndProperty WindowID="40030" WindowText="" WindowLeft="136" WindowTop="245" WindowHeight="32" WindowWidth="32" Visible="1" FixSize="0" Drag="0" Drop="0">
                <BackGroundMap BGmap="Slot32.dds">
                    <NorUV NorUVLeft="0" NorUVTop="0" NorUVWidth="32" NorUVHeight="32" />
                </BackGroundMap>
                <BaseCtrlProperty Tips="" FontFace="細明體" FontSize="10" FontColor="0" FontStyle="0" />
                <SlotNode />
            </BaseWndProperty>
            <Style ParentNode="40033" CtrlType="33554432" />
            <BaseWndProperty WindowID="40031" WindowText="" WindowLeft="172" WindowTop="245" WindowHeight="110" WindowWidth="16" Visible="1" FixSize="0" Drag="0" Drop="0">
                <BackGroundMap BGmap="Slot32.dds">
                    <NorUV NorUVLeft="0" NorUVTop="0" NorUVWidth="0" NorUVHeight="0" />
                </BackGroundMap>
                <BaseCtrlProperty Tips="" FontFace="細明體" FontSize="10" FontColor="16777215" FontStyle="1" />
                <TextNode TextAlign="0" MultiLine="0" />
            </BaseWndProperty>
            <Style ParentNode="40033" CtrlType="33554432" />
            <BaseWndProperty WindowID="40032" WindowText="" WindowLeft="172" WindowTop="260" WindowHeight="110" WindowWidth="16" Visible="1" FixSize="0" Drag="0" Drop="0">
                <BackGroundMap BGmap="Slot32.dds">
                    <NorUV NorUVLeft="0" NorUVTop="0" NorUVWidth="0" NorUVHeight="0" />
                </BackGroundMap>
                <BaseCtrlProperty Tips="" FontFace="細明體" FontSize="10" FontColor="16777215" FontStyle="1" />
                <TextNode TextAlign="0" MultiLine="0" />
            </BaseWndProperty>
            <Style ParentNode="10000" CtrlType="268435456" />
            <BaseWndProperty WindowID="40038" WindowText="" WindowLeft="293" WindowTop="240" WindowHeight="159" WindowWidth="41" Visible="1" FixSize="0" Drag="0" Drop="0">
                <BackGroundMap BGmap="uiobj12.dds">
                    <NorUV NorUVLeft="1147" NorUVTop="109" NorUVWidth="159" NorUVHeight="41" />
                </BackGroundMap>
                <BaseCtrlProperty Tips="" FontFace="細明體" FontSize="10" FontColor="0" FontStyle="0" />
                <PictureNode TextureClampMode="0">
                    <ForegroundUV ForegroundUVLeft="0" ForegroundUVTop="0" ForegroundUVWidth="10" ForegroundUVHeight="10" />
                </PictureNode>
            </BaseWndProperty>
            <Style ParentNode="40038" CtrlType="536870912" />
            <BaseWndProperty WindowID="40035" WindowText="" WindowLeft="299" WindowTop="245" WindowHeight="32" WindowWidth="32" Visible="1" FixSize="0" Drag="0" Drop="0">
                <BackGroundMap BGmap="Slot32.dds">
                    <NorUV NorUVLeft="0" NorUVTop="0" NorUVWidth="32" NorUVHeight="32" />
                </BackGroundMap>
                <BaseCtrlProperty Tips="" FontFace="細明體" FontSize="10" FontColor="0" FontStyle="0" />
                <SlotNode />
            </BaseWndProperty>
            <Style ParentNode="40038" CtrlType="33554432" />
            <BaseWndProperty WindowID="40036" WindowText="" WindowLeft="335" WindowTop="245" WindowHeight="110" WindowWidth="16" Visible="1" FixSize="0" Drag="0" Drop="0">
                <BackGroundMap BGmap="Slot32.dds">
                    <NorUV NorUVLeft="0" NorUVTop="0" NorUVWidth="0" NorUVHeight="0" />
                </BackGroundMap>
                <BaseCtrlProperty Tips="" FontFace="細明體" FontSize="10" FontColor="16777215" FontStyle="1" />
                <TextNode TextAlign="0" MultiLine="0" />
            </BaseWndProperty>
            <Style ParentNode="40038" CtrlType="33554432" />
            <BaseWndProperty WindowID="40037" WindowText="" WindowLeft="335" WindowTop="260" WindowHeight="110" WindowWidth="16" Visible="1" FixSize="0" Drag="0" Drop="0">
                <BackGroundMap BGmap="Slot32.dds">
                    <NorUV NorUVLeft="0" NorUVTop="0" NorUVWidth="0" NorUVHeight="0" />
                </BackGroundMap>
                <BaseCtrlProperty Tips="" FontFace="細明體" FontSize="10" FontColor="16777215" FontStyle="1" />
                <TextNode TextAlign="0" MultiLine="0" />
            </BaseWndProperty>
            <Style ParentNode="10000" CtrlType="268435456" />
            <BaseWndProperty WindowID="40043" WindowText="" WindowLeft="130" WindowTop="286" WindowHeight="159" WindowWidth="41" Visible="1" FixSize="0" Drag="0" Drop="0">
                <BackGroundMap BGmap="uiobj12.dds">
                    <NorUV NorUVLeft="1147" NorUVTop="109" NorUVWidth="159" NorUVHeight="41" />
                </BackGroundMap>
                <BaseCtrlProperty Tips="" FontFace="細明體" FontSize="10" FontColor="0" FontStyle="0" />
                <PictureNode TextureClampMode="0">
                    <ForegroundUV ForegroundUVLeft="0" ForegroundUVTop="0" ForegroundUVWidth="10" ForegroundUVHeight="10" />
                </PictureNode>
            </BaseWndProperty>
            <Style ParentNode="40043" CtrlType="536870912" />
            <BaseWndProperty WindowID="40040" WindowText="" WindowLeft="136" WindowTop="291" WindowHeight="32" WindowWidth="32" Visible="1" FixSize="0" Drag="0" Drop="0">
                <BackGroundMap BGmap="Slot32.dds">
                    <NorUV NorUVLeft="0" NorUVTop="0" NorUVWidth="32" NorUVHeight="32" />
                </BackGroundMap>
                <BaseCtrlProperty Tips="" FontFace="細明體" FontSize="10" FontColor="0" FontStyle="0" />
                <SlotNode />
            </BaseWndProperty>
            <Style ParentNode="40043" CtrlType="33554432" />
            <BaseWndProperty WindowID="40041" WindowText="" WindowLeft="172" WindowTop="291" WindowHeight="110" WindowWidth="16" Visible="1" FixSize="0" Drag="0" Drop="0">
                <BackGroundMap BGmap="Slot32.dds">
                    <NorUV NorUVLeft="0" NorUVTop="0" NorUVWidth="0" NorUVHeight="0" />
                </BackGroundMap>
                <BaseCtrlProperty Tips="" FontFace="細明體" FontSize="10" FontColor="16777215" FontStyle="1" />
                <TextNode TextAlign="0" MultiLine="0" />
            </BaseWndProperty>
            <Style ParentNode="40043" CtrlType="33554432" />
            <BaseWndProperty WindowID="40042" WindowText="" WindowLeft="172" WindowTop="306" WindowHeight="110" WindowWidth="16" Visible="1" FixSize="0" Drag="0" Drop="0">
                <BackGroundMap BGmap="Slot32.dds">
                    <NorUV NorUVLeft="0" NorUVTop="0" NorUVWidth="0" NorUVHeight="0" />
                </BackGroundMap>
                <BaseCtrlProperty Tips="" FontFace="細明體" FontSize="10" FontColor="16777215" FontStyle="1" />
                <TextNode TextAlign="0" MultiLine="0" />
            </BaseWndProperty>
            <Style ParentNode="10000" CtrlType="268435456" />
            <BaseWndProperty WindowID="40048" WindowText="" WindowLeft="293" WindowTop="286" WindowHeight="159" WindowWidth="41" Visible="1" FixSize="0" Drag="0" Drop="0">
                <BackGroundMap BGmap="uiobj12.dds">
                    <NorUV NorUVLeft="1147" NorUVTop="109" NorUVWidth="159" NorUVHeight="41" />
                </BackGroundMap>
                <BaseCtrlProperty Tips="" FontFace="細明體" FontSize="10" FontColor="0" FontStyle="0" />
                <PictureNode TextureClampMode="0">
                    <ForegroundUV ForegroundUVLeft="0" ForegroundUVTop="0" ForegroundUVWidth="10" ForegroundUVHeight="10" />
                </PictureNode>
            </BaseWndProperty>
            <Style ParentNode="40048" CtrlType="536870912" />
            <BaseWndProperty WindowID="40045" WindowText="" WindowLeft="299" WindowTop="291" WindowHeight="32" WindowWidth="32" Visible="1" FixSize="0" Drag="0" Drop="0">
                <BackGroundMap BGmap="Slot32.dds">
                    <NorUV NorUVLeft="0" NorUVTop="0" NorUVWidth="32" NorUVHeight="32" />
                </BackGroundMap>
                <BaseCtrlProperty Tips="" FontFace="細明體" FontSize="10" FontColor="0" FontStyle="0" />
                <SlotNode />
            </BaseWndProperty>
            <Style ParentNode="40048" CtrlType="33554432" />
            <BaseWndProperty WindowID="40046" WindowText="" WindowLeft="335" WindowTop="291" WindowHeight="110" WindowWidth="16" Visible="1" FixSize="0" Drag="0" Drop="0">
                <BackGroundMap BGmap="Slot32.dds">
                    <NorUV NorUVLeft="0" NorUVTop="0" NorUVWidth="0" NorUVHeight="0" />
                </BackGroundMap>
                <BaseCtrlProperty Tips="" FontFace="細明體" FontSize="10" FontColor="16777215" FontStyle="1" />
                <TextNode TextAlign="0" MultiLine="0" />
            </BaseWndProperty>
            <Style ParentNode="40048" CtrlType="33554432" />
            <BaseWndProperty WindowID="40047" WindowText="" WindowLeft="335" WindowTop="306" WindowHeight="110" WindowWidth="16" Visible="1" FixSize="0" Drag="0" Drop="0">
                <BackGroundMap BGmap="Slot32.dds">
                    <NorUV NorUVLeft="0" NorUVTop="0" NorUVWidth="0" NorUVHeight="0" />
                </BackGroundMap>
                <BaseCtrlProperty Tips="" FontFace="細明體" FontSize="10" FontColor="16777215" FontStyle="1" />
                <TextNode TextAlign="0" MultiLine="0" />
            </BaseWndProperty>
            <Style ParentNode="10000" CtrlType="262144" />
            <BaseWndProperty WindowID="33000" WindowText="" WindowLeft="267" WindowTop="337" WindowHeight="9" WindowWidth="13" Visible="1" FixSize="0" Drag="0" Drop="0">
                <BackGroundMap BGmap="main.dds">
                    <NorUV NorUVLeft="786" NorUVTop="297" NorUVWidth="9" NorUVHeight="13" />
                </BackGroundMap>
                <BaseCtrlProperty Tips="" FontFace="細明體" FontSize="10" FontColor="16777215" FontStyle="0" />
                <ButtonNode BtnState="0">
                    <FocusUV FocusUVLeft="786" FocusUVTop="311" FocusUVWidth="9" FocusUVHeight="13" />
                    <DownUV DownUVLeft="786" DownUVTop="325" DownUVWidth="9" DownUVHeight="13" />
                    <DisableUV DisableUVLeft="786" DisableUVTop="339" DisableUVWidth="9" DisableUVHeight="13" />
                </ButtonNode>
            </BaseWndProperty>
            <Style ParentNode="10000" CtrlType="262144" />
            <BaseWndProperty WindowID="33001" WindowText="" WindowLeft="309" WindowTop="337" WindowHeight="9" WindowWidth="13" Visible="1" FixSize="0" Drag="0" Drop="0">
                <BackGroundMap BGmap="main.dds">
                    <NorUV NorUVLeft="796" NorUVTop="297" NorUVWidth="9" NorUVHeight="13" />
                </BackGroundMap>
                <BaseCtrlProperty Tips="" FontFace="細明體" FontSize="10" FontColor="16777215" FontStyle="0" />
                <ButtonNode BtnState="0">
                    <FocusUV FocusUVLeft="796" FocusUVTop="311" FocusUVWidth="9" FocusUVHeight="13" />
                    <DownUV DownUVLeft="796" DownUVTop="325" DownUVWidth="9" DownUVHeight="13" />
                    <DisableUV DisableUVLeft="796" DisableUVTop="339" DisableUVWidth="9" DisableUVHeight="13" />
                </ButtonNode>
            </BaseWndProperty>
            <Style ParentNode="10000" CtrlType="33554432" />
            <BaseWndProperty WindowID="21000" WindowText="1/7" WindowLeft="280" WindowTop="336" WindowHeight="23" WindowWidth="16" Visible="1" FixSize="0" Drag="0" Drop="0">
                <BackGroundMap BGmap="Slot32.dds">
                    <NorUV NorUVLeft="0" NorUVTop="0" NorUVWidth="0" NorUVHeight="0" />
                </BackGroundMap>
                <BaseCtrlProperty Tips="" FontFace="細明體" FontSize="9" FontColor="16777215" FontStyle="0" />
                <TextNode TextAlign="1" MultiLine="0" />
            </BaseWndProperty>
        </Container_Node>
    </BaseWndProperty>
</Root_Node>
